revs/client.py
revs/version.py
revs-1.0.1.dist-info/LICENSE
revs-1.0.1.dist-info/METADATA
revs-1.0.1.dist-info/WHEEL
revs-1.0.1.dist-info/top_level.txt
revs-1.0.1.dist-info/zip-safe
revs-1.0.1.dist-info/RECORD
