Metadata-Version: 2.1
Name: revs
Version: 1.0.1
Summary: Python 3 library for telegram bots
Home-page: https://github.com/fenixinvitado2021/revistas
Author: RayServer
Author-email: obysoftt@gmail.com
License: The Unlicense (Unlicense)
Keywords: telegram,download,stream,bots
Classifier: Development Status :: 5 - Production/Stable
Classifier: Environment :: Console
Classifier: Intended Audience :: Developers
Classifier: License :: OSI Approved :: The Unlicense (Unlicense)
Classifier: Natural Language :: English
Classifier: Operating System :: OS Independent
Classifier: Programming Language :: Python :: 3.6
Classifier: Programming Language :: Python :: 3.7
Classifier: Programming Language :: Python :: 3.8
Classifier: Programming Language :: Python :: 3.9
Classifier: Programming Language :: Python
Classifier: Topic :: Internet
Classifier: Topic :: Software Development :: Libraries :: Python Modules
Classifier: Topic :: Utilities
Requires-Python: >=3.6
License-File: LICENSE
Requires-Dist: bs4
Requires-Dist: requests
